odoo/addons/sale_coupon_chatter/README.rst
odoo/addons/sale_coupon_chatter/__init__.py
odoo/addons/sale_coupon_chatter/__manifest__.py
odoo/addons/sale_coupon_chatter/i18n/sale_coupon_chatter.pot
odoo/addons/sale_coupon_chatter/models/__init__.py
odoo/addons/sale_coupon_chatter/models/sale_coupon_program.py
odoo/addons/sale_coupon_chatter/readme/CONTRIBUTORS.rst
odoo/addons/sale_coupon_chatter/readme/DESCRIPTION.rst
odoo/addons/sale_coupon_chatter/readme/USAGE.rst
odoo/addons/sale_coupon_chatter/static/description/icon.png
odoo/addons/sale_coupon_chatter/static/description/index.html
odoo/addons/sale_coupon_chatter/views/sale_coupon_program_views.xml
odoo13_addon_sale_coupon_chatter-13.0.1.0.1.dev4.dist-info/METADATA
odoo13_addon_sale_coupon_chatter-13.0.1.0.1.dev4.dist-info/WHEEL
odoo13_addon_sale_coupon_chatter-13.0.1.0.1.dev4.dist-info/top_level.txt
odoo13_addon_sale_coupon_chatter-13.0.1.0.1.dev4.dist-info/RECORD
